durasftp/__init__.py
durasftp/__main__.py
durasftp/config.py
durasftp/common/__init__.py
durasftp/common/code_quality.py
durasftp/common/log/__init__.py
durasftp/common/log/log_file_action.py
durasftp/common/log/log_formatter.py
durasftp/common/log/log_level_action.py
durasftp/common/networking/__init__.py
durasftp/common/networking/echo_server.py
durasftp/common/networking/port_forwarder.py
durasftp/common/networking/stoppable_thread.py
durasftp/common/sftp/__init__.py
durasftp/common/sftp/action.py
durasftp/common/sftp/action_codes.py
durasftp/common/sftp/action_list.py
durasftp/common/sftp/connection.py
durasftp/common/sftp/mirrorer.py
durasftp-1.0.0.dist-info/LICENSE
durasftp-1.0.0.dist-info/METADATA
durasftp-1.0.0.dist-info/WHEEL
durasftp-1.0.0.dist-info/entry_points.txt
durasftp-1.0.0.dist-info/top_level.txt
durasftp-1.0.0.dist-info/RECORD
