Metadata-Version: 2.1
Name: durasftp
Version: 1.0.0
Summary: Durable SFTP connections
Home-page: https://github.com/maludwig/durasftp
Author: maludwig
Author-email: mitchell.ludwig@gmail.com
License: MIT
Platform: UNKNOWN
Classifier: License :: OSI Approved :: MIT License
Classifier: Programming Language :: Python
Classifier: Programming Language :: Python :: 3
Requires-Python: >=3.5
Requires-Dist: pysftp (>=0.2.9)
Requires-Dist: arrow (>=0.14.4)
